README.rst
setup.py
WAUnit/__init__.py
WAUnit/main.py
WAUnit/setup.py
WAUnit/waunit_parsers.py
WAUnit/waunit_utils.py
waunit.egg-info/PKG-INFO
waunit.egg-info/SOURCES.txt
waunit.egg-info/dependency_links.txt
waunit.egg-info/entry_points.txt
waunit.egg-info/pbr.json
waunit.egg-info/requires.txt
waunit.egg-info/top_level.txt