Metadata-Version: 1.1
Name: waunit
Version: 0.0.4a1
Summary: Web analytics unit testing framework
Home-page: https://github.com/joaolcorreia/WAUnit
Author: Joao Correia
Author-email: joao.correia@gmail.com
License: Apache Software License
Keywords: google adobe omniture snowplow analytics quality assurance
Platform: UNKNOWN
Classifier: Development Status :: 3 - Alpha
Classifier: Intended Audience :: Developers
Classifier: Topic :: Internet :: Log Analysis
Classifier: Topic :: Software Development :: Quality Assurance
Classifier: License :: OSI Approved :: Apache Software License
Classifier: Programming Language :: Python :: 2.7
